ApkPatcher/AES.py
ApkPatcher/AES.smali
ApkPatcher/APK_PATCHER.py
ApkPatcher/Ads_Patch.py
ApkPatcher/Anti_Splits.py
ApkPatcher/Argparse.py
ApkPatcher/CRC.py
ApkPatcher/C_M.py
ApkPatcher/Cert_Net_Config.py
ApkPatcher/Decompile_Compile.py
ApkPatcher/Files_Check.py
ApkPatcher/Flutter_SSL_Patch.py
ApkPatcher/Instruction_Credit.py
ApkPatcher/Manifest_Patch.py
ApkPatcher/Package.py
ApkPatcher/Pairip_CoreX.py
ApkPatcher/Random_INFO.py
ApkPatcher/Scan.py
ApkPatcher/Smali_Patch.py
ApkPatcher/Spoof_Patch.py
ApkPatcher/__init__.py
ApkPatcher/lib_Pairip_CoreX.so
apkpatcher_install-1.0.dist-info/licenses/LICENSE
apkpatcher_install-1.0.dist-info/METADATA
apkpatcher_install-1.0.dist-info/WHEEL
apkpatcher_install-1.0.dist-info/entry_points.txt
apkpatcher_install-1.0.dist-info/top_level.txt
apkpatcher_install-1.0.dist-info/RECORD
