Metadata-Version: 2.4
Name: ApkPatcher-install
Version: 1.0
Summary: Smali Patcher ( Bypass 𒁍 SSL & Flutter SSL, VPN, USB Debugging, Screen Restrict, One Device Login, Spoof Info & Package Detection, Ads, AES Logs Inject )
Author-email: RK_TECHNO_INDIA <TechnoIndian786@gmail.com>
License: MIT License
Project-URL: Homepage, https://github.com/TechnoIndian/ApkPatcher
Project-URL: Repository, https://github.com/TechnoIndian/ApkPatcher.git
Project-URL: Issues, https://github.com/TechnoIndian/ApkPatcher/issues
Keywords: ApkPatcher
Classifier: Programming Language :: Python :: 3
Classifier: Programming Language :: Python :: 3.12
Classifier: Operating System :: OS Independent
Classifier: Topic :: Software Development :: Assemblers
Requires-Python: >=3.12
License-File: LICENSE
Requires-Dist: requests
Requires-Dist: r2pipe
Requires-Dist: asn1crypto
Requires-Dist: multiprocess
Dynamic: license-file
